pyproject.toml
screenpro/__init__.py
screenpro/__main__.py
screenpro/assays/__init__.py
screenpro/dashboard/__init__.py
screenpro/load.py
screenpro/main.py
screenpro/ngs/__init__.py
screenpro/ngs/cas12.py
screenpro/ngs/cas9.py
screenpro/phenoscore/__init__.py
screenpro/phenoscore/_annotate.py
screenpro/phenoscore/delta.py
screenpro/phenoscore/deseq.py
screenpro/phenoscore/evaluate.py
screenpro/phenoscore/phenostat.py
screenpro/plotting/__init__.py
screenpro/plotting/_rank.py
screenpro/plotting/_utils.py
screenpro/plotting/pheno_plots.py
screenpro/plotting/qc_plots.py
screenpro/preprocessing.py
screenpro2-0.5.0.dist-info/LICENSE
screenpro2-0.5.0.dist-info/METADATA
screenpro2-0.5.0.dist-info/WHEEL
screenpro2-0.5.0.dist-info/entry_points.txt
screenpro2-0.5.0.dist-info/RECORD
