Metadata-Version: 2.3
Name: ScreenPro2
Version: 0.5.0
Summary: Flexible analysis of high-content CRISPR screening
License: MIT
Keywords: CRISPR,screening,bioinformatics
Author: Abe Arab
Author-email: abea@arcinstitute.org
Requires-Python: >=3.9
Classifier: License :: OSI Approved :: MIT License
Classifier: Programming Language :: Python :: 3
Classifier: Programming Language :: Python :: 3.9
Classifier: Programming Language :: Python :: 3.10
Classifier: Programming Language :: Python :: 3.11
Classifier: Programming Language :: Python :: 3.12
Classifier: Programming Language :: Python :: 3.13
Project-URL: Homepage, https://github.com/ArcInstitute/ScreenPro2
Project-URL: Repository, https://github.com/ArcInstitute/ScreenPro2
